LICENSE.txt
MANIFEST.in
README.md
setup.cfg
setup.py
PyBBIO.egg-info/PKG-INFO
PyBBIO.egg-info/SOURCES.txt
PyBBIO.egg-info/dependency_links.txt
PyBBIO.egg-info/requires.txt
PyBBIO.egg-info/top_level.txt
bbio/__init__.py
bbio/bbio.py
bbio/common.py
bbio/libraries/__init__.py
bbio/libraries/example.py
bbio/libraries/ADS786x/__init__.py
bbio/libraries/ADS786x/ads786x.py
bbio/libraries/ADT7310/README.md
bbio/libraries/ADT7310/__init__.py
bbio/libraries/ADT7310/adt7310.py
bbio/libraries/ADXL345/ADXL345.py
bbio/libraries/ADXL345/__init__.py
bbio/libraries/BBIOServer/__init__.py
bbio/libraries/BBIOServer/bbio_server.py
bbio/libraries/BBIOServer/src/footer.html
bbio/libraries/BBIOServer/src/functions.js
bbio/libraries/BBIOServer/src/header.html
bbio/libraries/BBIOServer/src/index.html.template
bbio/libraries/BBIOServer/src/jquery-1.11.1.min.js
bbio/libraries/BBIOServer/src/mobile.css
bbio/libraries/BBIOServer/src/sidebar.html
bbio/libraries/BBIOServer/src/style.css
bbio/libraries/BMP183/BMP183.py
bbio/libraries/BMP183/__init__.py
bbio/libraries/DACx311/__init__.py
bbio/libraries/DACx311/dacx311.py
bbio/libraries/EventIO/__init__.py
bbio/libraries/EventIO/eventio.py
bbio/libraries/Graphics/__init__.py
bbio/libraries/Graphics/graphics.py
bbio/libraries/GridEYE/GridEYE.py
bbio/libraries/GridEYE/__init__.py
bbio/libraries/HTU21D/HTU21D.py
bbio/libraries/HTU21D/__init__.py
bbio/libraries/IoT/__init__.py
bbio/libraries/IoT/phant.py
bbio/libraries/IoT/thingspeak.py
bbio/libraries/LiquidCrystal/LiquidCrystal.py
bbio/libraries/LiquidCrystal/__init__.py
bbio/libraries/MAX31855/__init__.py
bbio/libraries/MAX31855/max31855.py
bbio/libraries/MAX7219/__init__.py
bbio/libraries/MAX7219/max7219.py
bbio/libraries/MLX90614/MLX90614.py
bbio/libraries/MLX90614/__init__.py
bbio/libraries/MMA7660/README.md
bbio/libraries/MMA7660/__init__.py
bbio/libraries/MMA7660/mma7660.py
bbio/libraries/RotaryEncoder/README.md
bbio/libraries/RotaryEncoder/__init__.py
bbio/libraries/RotaryEncoder/rotary_encoder.py
bbio/libraries/SIM800/SIM800.py
bbio/libraries/SIM800/__init__.py
bbio/libraries/SafeProcess/__init__.py
