Metadata-Version: 1.1
Name: PyBBIO
Version: 0.10
Summary: A Python library for Arduino-style hardware IO support on the BeagleBone and BeagleBone Black
Home-page: https://github.com/graycatlabs/PyBBIO/wiki
Author: Alexander Hiam
Author-email: alex@graycat.io
License: MIT License
Download-URL: https://github.com/graycatlabs/PyBBIO/tarball/v0.10
Keywords: BeagleBone,BeagleBone Black,IO,GPIO,ADC,PWM,I2C,SPI,bbio,eQEP
Platform: BeagleBone
Platform: BeagleBone Black
Classifier: License :: OSI Approved :: MIT License
Classifier: Operating System :: POSIX :: Linux
Classifier: Topic :: Software Development :: Embedded Systems
Classifier: Topic :: Software Development :: Libraries :: Python Modules
Classifier: Topic :: System :: Hardware
